tornado_jsonrpc.py
tornado_jsonrpc-1.0.5.dist-info/LICENSE
tornado_jsonrpc-1.0.5.dist-info/METADATA
tornado_jsonrpc-1.0.5.dist-info/WHEEL
tornado_jsonrpc-1.0.5.dist-info/top_level.txt
tornado_jsonrpc-1.0.5.dist-info/RECORD
