Metadata-Version: 2.1
Name: tornado-jsonrpc
Version: 1.0.5
Summary: jsonrpc implementation for tornado
Home-page: https://github.com/Pavel-Egorov/tornado_jsonrpc
Author: Pavel Egorov
Author-email: paveg.sp@gmail.com
Maintainer: Pavel Egorov
Maintainer-email: paveg.sp@gmail.com
License: Apache
Keywords: tornado,jsonrpc,rpc,handler
Platform: UNKNOWN
Classifier: Development Status :: 5 - Production/Stable
Classifier: Intended Audience :: Developers
Classifier: Natural Language :: English
Classifier: License :: OSI Approved :: Apache Software License
Classifier: Operating System :: OS Independent
Classifier: Programming Language :: Python
Classifier: Programming Language :: Python :: 3.5
Classifier: Programming Language :: Python :: 3.6
Classifier: Programming Language :: Python :: 3.7
Classifier: Programming Language :: Python :: 3.8
Classifier: Programming Language :: Python :: 3.9
Classifier: Topic :: Software Development :: Libraries :: Python Modules
License-File: LICENSE
Requires-Dist: tornado (>=4.0)
